{
    "parameterSets": {
        "M4_Bolt_Tray_6x3x0.75": {
            "Block_Handle_Height": "0.375",
            "Block_Width_or_Bar_Diameter": "0.25",
            "Block_or_Bar_Handle_Length": "1",
            "Build_Mode": "Custom_Divisions_per_Column_or_Row",
            "Corner_Roundness": "0.5",
            "Create_A_Lid": "false",
            "Cup_Along_Length": "1",
            "Cups_Across_Width": "1",
            "Custom_Col_Row_Ratios": "[1, 5, 3, 3, 3, 1.5, 3, 0, 4, 0, 4, 0, 3, 0, 2, 0, 5]",
            "Custom_Division_List": "",
            "Divider_Wall_Thickness": "0.07",
            "Finger_Hole_Diameter": "0.5",
            "Finger_Hole_Position": "2",
            "Finger_Hole_Style": "Square",
            "Floor_Thickness": "0.07",
            "Interlock_Gap": "0.003",
            "Interlock_Height": "0.1",
            "Lengthwise_Cup_Ratios": "[1, 1, 1, 1, 1]",
            "Lid_Handle_Style": "No Handle",
            "Lid_Thickness": "0.07",
            "Rotate_Handle": "0",
            "Scale_Units": "25.4",
            "Square_Cup_Size": "1",
            "Tray_Height": "0.75",
            "Tray_Length": "6",
            "Tray_Wall_Thickness": "0.07",
            "Tray_Width": "3",
            "Widthwise_Cup_Ratios": "[1, 1, 1, 1, 1]"
        },
        "M4_Bolt_Tray_8x4x1": {
            "Block_Handle_Height": "0.375",
            "Block_Width_or_Bar_Diameter": "0.25",
            "Block_or_Bar_Handle_Length": "1",
            "Build_Mode": "Custom_Divisions_per_Column_or_Row",
            "Corner_Roundness": "0.5",
            "Create_A_Lid": "false",
            "Cup_Along_Length": "1",
            "Cups_Across_Width": "1",
            "Custom_Col_Row_Ratios": "[1, 5, 3, 3, 3, 1.5, 3, 0, 4, 0, 4, 0, 3, 0, 2, 0, 5]",
            "Custom_Division_List": "",
            "Divider_Wall_Thickness": "0.07",
            "Finger_Hole_Diameter": "0.5",
            "Finger_Hole_Position": "2",
            "Finger_Hole_Style": "Square",
            "Floor_Thickness": "0.07",
            "Interlock_Gap": "0.003",
            "Interlock_Height": "0.1",
            "Lengthwise_Cup_Ratios": "[1, 1, 1, 1, 1]",
            "Lid_Handle_Style": "No Handle",
            "Lid_Thickness": "0.07",
            "Rotate_Handle": "0",
            "Scale_Units": "25.4",
            "Square_Cup_Size": "1",
            "Tray_Height": "1",
            "Tray_Length": "8",
            "Tray_Wall_Thickness": "0.07",
            "Tray_Width": "4",
            "Widthwise_Cup_Ratios": "[1, 1, 1, 1, 1]"
        },
        "M2_M3_Bolt_Tray6x3x0.75": {
            "Block_Handle_Height": "0.375",
            "Block_Width_or_Bar_Diameter": "0.25",
            "Block_or_Bar_Handle_Length": "1",
            "Build_Mode": "Custom_Divisions_per_Column_or_Row",
            "Corner_Roundness": "0.5",
            "Create_A_Lid": "false",
            "Cup_Along_Length": "1",
            "Cups_Across_Width": "1",
            "Custom_Col_Row_Ratios": "[1, 5, 2, 2, 2, 1.5, 2, 0, 3, 0, 3, 0, 3, 0, 2, 0, 5]",
            "Custom_Division_List": "",
            "Divider_Wall_Thickness": "0.07",
            "Finger_Hole_Diameter": "0.5",
            "Finger_Hole_Position": "2",
            "Finger_Hole_Style": "Square",
            "Floor_Thickness": "0.07",
            "Interlock_Gap": "0.003",
            "Interlock_Height": "0.1",
            "Lengthwise_Cup_Ratios": "[1, 1, 1, 1, 1]",
            "Lid_Handle_Style": "No Handle",
            "Lid_Thickness": "0.07",
            "Rotate_Handle": "0",
            "Scale_Units": "25.4",
            "Square_Cup_Size": "1",
            "Tray_Height": "0.75",
            "Tray_Length": "6",
            "Tray_Wall_Thickness": "0.07",
            "Tray_Width": "3",
            "Widthwise_Cup_Ratios": "[1, 1, 1, 1, 1]"
        },
        "M2_M3_Bolt_Tray_8x4x1": {
            "Block_Handle_Height": "0.375",
            "Block_Width_or_Bar_Diameter": "0.25",
            "Block_or_Bar_Handle_Length": "1",
            "Build_Mode": "Custom_Divisions_per_Column_or_Row",
            "Corner_Roundness": "0.5",
            "Create_A_Lid": "false",
            "Cup_Along_Length": "1",
            "Cups_Across_Width": "1",
            "Custom_Col_Row_Ratios": "[1, 5, 2, 2, 2, 1.5, 2, 0, 3, 0, 3, 0, 3, 0, 2, 0, 5]",
            "Custom_Division_List": "",
            "Divider_Wall_Thickness": "0.07",
            "Finger_Hole_Diameter": "0.5",
            "Finger_Hole_Position": "2",
            "Finger_Hole_Style": "Square",
            "Floor_Thickness": "0.07",
            "Interlock_Gap": "0.003",
            "Interlock_Height": "0.1",
            "Lengthwise_Cup_Ratios": "[1, 1, 1, 1, 1]",
            "Lid_Handle_Style": "No Handle",
            "Lid_Thickness": "0.07",
            "Rotate_Handle": "0",
            "Scale_Units": "25.4",
            "Square_Cup_Size": "1",
            "Tray_Height": "1",
            "Tray_Length": "8",
            "Tray_Wall_Thickness": "0.07",
            "Tray_Width": "4",
            "Widthwise_Cup_Ratios": "[1, 1, 1, 1, 1]"
        },
        "Knife_Tray_Insert": {
            "Build_Mode": "Custom_Divisions_per_Column_or_Row",
            "Corner_Roundness": "0.5",
            "Create_A_Lid": "false",
            "Cups_Across_Width": "4",
            "Cups_Along_Length": "1",
            "Custom_Col_Row_Ratios": "[1, 2, 1, 7, 0, 1, 0, 6]",
            "Custom_Division_List": "[0, 0.333, 0, 0.666, 0, 0.666, 0.333, 1, 1, 0.333, 0.333, 1, 1, 0.666, 0, 0.666]",
            "Divider_Wall_Height_Scale": "0.65",
            "Divider_Wall_Thickness": "0.07",
            "Finger_Hole_Diameter": "0.75",
            "Finger_Hole_Position": "1",
            "Finger_Hole_Style": "Round",
            "Finger_Slot_Lift": "0.15",
            "Finger_Slot_Position": "0.77",
            "Finger_Slot_Radius": "2.02",
            "Finger_Slot_Width": "0.1",
            "Floor_Thickness": "0.07",
            "Insert_Tray_Gap": "0.015",
            "Insert_Tray_Height": "0",
            "Interlock_Divider_Wall_Recess": "0",
            "Interlock_Gap": "0.003",
            "Interlock_Height": "0",
            "Interlocking_Lid": "true",
            "Label_Lid": "true",
            "Lengthwise_Cup_Ratios": "[1, 2, 1]",
            "Lengthwise_Finger_Slot": "false",
            "Lid_Handle_Style": "Finger_Holes",
            "Lid_Thickness": "0.05",
            "Make_Finger_Slots": "true",
            "Make_Insert_Tray": "true",
            "Number_Of_Finger_Holes": "2",
            "Rotate_Handle": "0",
            "Scale_Units": "25.4",
            "Square_Cup_Size": "1",
            "Tray_Height": "0.75",
            "Tray_Length": "8",
            "Tray_Wall_Thickness": "0.07",
            "Tray_Width": "4",
            "Widthwise_Cup_Ratios": "[1, 1]"
        },
        "Knife_Tray_Main": {
            "Add_Corner_Posts": "true",
            "Build_Mode": "Just_the_Tray",
            "Corner_Post_Size": "0.25",
            "Corner_Roundness": "0.5",
            "Create_A_Lid": "false",
            "Cups_Across_Width": "1",
            "Cups_Along_Length": "1",
            "Custom_Col_Row_Ratios": "[1, 5, 2, 2, 2, 1.5, 2, 0, 3, 0, 3, 0, 3, 0, 2, 0, 5]",
            "Custom_Division_List": "[\"-\", 0.333, 0, 0.666, \"-\", 0.666, 0.333, 1, \"|\", 0.333, 0.333, 1, \"|\", 0.666, 0, 0.666]",
            "Divider_Wall_Height_Scale": "1",
            "Divider_Wall_Thickness": "0.07",
            "Finger_Hole_Diameter": "0.75",
            "Finger_Hole_Position": "1",
            "Finger_Hole_Style": "Round",
            "Finger_Slot_Lift": "1",
            "Finger_Slot_Position": "0.5",
            "Finger_Slot_Radius": "1",
            "Finger_Slot_Width": "0",
            "Floor_Thickness": "0.07",
            "Insert_Tray_Gap": "0.03",
            "Insert_Tray_Height": "0.75",
            "Interlock_Divider_Wall_Recess": "0",
            "Interlock_Gap": "0.003",
            "Interlock_Height": "0.05",
            "Interlocking_Lid": "false",
            "Label_Lid": "false",
            "Lengthwise_Cup_Ratios": "[1, 1, 1, 1, 1]",
            "Lengthwise_Finger_Slot": "true",
            "Lid_Handle_Style": "Finger_Holes",
            "Lid_Thickness": "0.07",
            "Make_Finger_Slots": "false",
            "Make_Insert_Tray": "false",
            "Number_Of_Finger_Holes": "1",
            "Rotate_Handle": "0",
            "Scale_Units": "25.4",
            "Square_Cup_Size": "1",
            "Tray_Height": "2",
            "Tray_Length": "8",
            "Tray_Wall_Thickness": "0.07",
            "Tray_Width": "4",
            "Widthwise_Cup_Ratios": "[1, 1, 1, 1, 1]"
        },
        "M@-M3_Bolt_Tray_With_Lid_8x4x1": {
            "Add_Corner_Posts": "false",
            "Build_Mode": "Custom_Divisions_per_Column_or_Row",
            "Corner_Post_Size": "0.2",
            "Corner_Roundness": "0.5",
            "Create_A_Lid": "true",
            "Cups_Across_Width": "1",
            "Cups_Along_Length": "1",
            "Custom_Col_Row_Ratios": "[1, 5, 2, 2, 2, 1.5, 2, 0, 3, 0, 3, 0, 3, 0, 2, 0, 5]",
            "Custom_Division_List": "[\"-\", 0.333, 0, 0.666, \"-\", 0.666, 0.333, 1, \"|\", 0.333, 0.333, 1, \"|\", 0.666, 0, 0.666]",
            "Divider_Wall_Height_Scale": "1",
            "Divider_Wall_Thickness": "0.07",
            "Finger_Hole_Diameter": "0.75",
            "Finger_Hole_Position": "0.98",
            "Finger_Hole_Style": "Round",
            "Finger_Slot_Lift": "1",
            "Finger_Slot_Position": "0.5",
            "Finger_Slot_Radius": "1",
            "Finger_Slot_Width": "0",
            "Floor_Thickness": "0.07",
            "Insert_Tray_Gap": "0.03",
            "Insert_Tray_Height": "0",
            "Interlock_Divider_Wall_Recess": "0",
            "Interlock_Gap": "0.003",
            "Interlock_Height": "0.1",
            "Interlocking_Lid": "false",
            "Label_Lid": "true",
            "Lengthwise_Cup_Ratios": "[1, 1, 1, 1, 1]",
            "Lengthwise_Finger_Slot": "true",
            "Lid_Handle_Style": "Finger_Holes",
            "Lid_Thickness": "0",
            "Make_Finger_Slots": "false",
            "Make_Insert_Tray": "false",
            "Make_Room_For_Recessed_Lid_And_Stacked_Tray": "true",
            "Number_Of_Finger_Holes": "2",
            "Rotate_Handle": "0",
            "Scale_Units": "25.4",
            "Square_Cup_Size": "1",
            "Tray_Height": "1",
            "Tray_Length": "8",
            "Tray_Wall_Thickness": "0.07",
            "Tray_Width": "4",
            "Widthwise_Cup_Ratios": "[1, 1, 1, 1, 1]"
        },
        "Impereal_Defaults": {
            "Add_Corner_Posts": "false",
            "Build_Mode": "Just_the_Tray",
            "Corner_Post_Size": "0.2",
            "Corner_Roundness": "0.5",
            "Create_A_Lid": "false",
            "Cups_Across_Width": "1",
            "Cups_Along_Length": "1",
            "Custom_Col_Row_Ratios": "[1, 5, 2, 2, 2, 1.5, 2, 0, 3, 0, 3, 0, 3, 0, 2, 0, 5]",
            "Custom_Division_List": "[\"-\", 0.333, 0, 0.666, \"-\", 0.666, 0.333, 1, \"|\", 0.333, 0.333, 1, \"|\", 0.666, 0, 0.666]",
            "Divider_Wall_Height_Scale": "1",
            "Divider_Wall_Thickness": "0.07",
            "Finger_Hole_Diameter": "0.75",
            "Finger_Hole_Position": "1",
            "Finger_Hole_Style": "Round",
            "Finger_Slot_Lift": "1",
            "Finger_Slot_Position": "0.5",
            "Finger_Slot_Radius": "1",
            "Finger_Slot_Width": "0",
            "Floor_Thickness": "0.07",
            "Insert_Tray_Gap": "0.03",
            "Insert_Tray_Height": "0",
            "Interlock_Divider_Wall_Recess": "0",
            "Interlock_Gap": "0.03",
            "Interlock_Height": "0.1",
            "Interlocking_Lid": "false",
            "Label_Lid": "false",
            "Label_Lid_Style": "Raised",
            "Lengthwise_Cup_Ratios": "[1, 1, 1, 1, 1]",
            "Lengthwise_Finger_Slot": "true",
            "Lid_Handle_Style": "Finger_Holes",
            "Lid_Thickness": "0.07",
            "Make_Finger_Slots": "false",
            "Make_Insert_Tray": "false",
            "Make_Room_For_Recessed_Lid_And_Stacked_Tray": "false",
            "Number_Of_Finger_Holes": "1",
            "Rotate_Handle": "0",
            "Scale_Units": "25.4",
            "Square_Cup_Size": "1",
            "Tray_Height": "1",
            "Tray_Length": "8",
            "Tray_Wall_Thickness": "0.07",
            "Tray_Width": "4",
            "Widthwise_Cup_Ratios": "[1, 1, 1, 1, 1]"
        },
        "Metric_Defaults": {
            "Add_Corner_Posts": "false",
            "Build_Mode": "Just_the_Tray",
            "Corner_Post_Size": "0.5",
            "Corner_Roundness": "1",
            "Create_A_Lid": "false",
            "Cups_Across_Width": "1",
            "Cups_Along_Length": "1",
            "Custom_Col_Row_Ratios": "[1, 5, 2, 2, 2, 1.5, 2, 0, 3, 0, 3, 0, 3, 0, 2, 0, 5]",
            "Custom_Division_List": "[\"-\", 0.333, 0, 0.666, \"-\", 0.666, 0.333, 1, \"|\", 0.333, 0.333, 1, \"|\", 0.666, 0, 0.666]",
            "Divider_Wall_Height_Scale": "1",
            "Divider_Wall_Thickness": "0.17",
            "Finger_Hole_Diameter": "2.2",
            "Finger_Hole_Position": "1",
            "Finger_Hole_Style": "Round",
            "Finger_Slot_Lift": "1",
            "Finger_Slot_Position": "0.5",
            "Finger_Slot_Radius": "2",
            "Finger_Slot_Width": "0",
            "Floor_Thickness": "0.17",
            "Insert_Tray_Gap": "0.1",
            "Insert_Tray_Height": "0",
            "Interlock_Divider_Wall_Recess": "0",
            "Interlock_Gap": "0.013",
            "Interlock_Height": "0.15",
            "Interlocking_Lid": "false",
            "Label_Lid": "false",
            "Label_Lid_Style": "Raised",
            "Lengthwise_Cup_Ratios": "[1, 1, 1, 1, 1]",
            "Lengthwise_Finger_Slot": "true",
            "Lid_Handle_Style": "Finger_Holes",
            "Lid_Thickness": "0.17",
            "Make_Finger_Slots": "false",
            "Make_Insert_Tray": "false",
            "Make_Room_For_Recessed_Lid_And_Stacked_Tray": "false",
            "Number_Of_Finger_Holes": "1",
            "Rotate_Handle": "0",
            "Scale_Units": "10",
            "Square_Cup_Size": "1",
            "Tray_Height": "2.5",
            "Tray_Length": "20",
            "Tray_Wall_Thickness": "0.17",
            "Tray_Width": "10",
            "Widthwise_Cup_Ratios": "[1, 1, 1, 1, 1]"
        },
        "Slide_Box_2x2": {
            "Add_Corner_Posts": "false",
            "Box_Top_Height": "1",
            "Box_Top_Interlock_Height": "0.08",
            "Box_Top_Interlock_Type": "Shell",
            "Build_Mode": "Storage_Slots",
            "Corner_Post_Size": "0.2",
            "Corner_Roundness": "0.5",
            "Create_A_Box_Top": "true",
            "Create_A_Lid": "false",
            "Cups_Across_Width": "1",
            "Cups_Along_Length": "1",
            "Custom_Col_Row_Ratios": "[1, 5, 2, 2, 2, 1.5, 2, 0, 3, 0, 3, 0, 3, 0, 2, 0, 5]",
            "Custom_Division_List": "[\"-\", 0.333, 0, 0.666, \"-\", 0.666, 0.333, 1, \"|\", 0.333, 0.333, 1, \"|\", 0.666, 0, 0.666]",
            "Dimensions_Are_External": "false",
            "Divider_Wall_Height_Scale": "1",
            "Divider_Wall_Thickness": "0.07",
            "Finger_Hole_Diameter": "0.75",
            "Finger_Hole_Position": "1",
            "Finger_Hole_Style": "Round",
            "Finger_Slot_Lift": "1",
            "Finger_Slot_Position": "0.5",
            "Finger_Slot_Radius": "1",
            "Finger_Slot_Width": "0",
            "Floor_Thickness": "0.07",
            "Insert_Tray_Gap": "0.03",
            "Insert_Tray_Height": "0",
            "Interlock_Divider_Wall_Recess": "0.05",
            "Interlock_Gap": "0.008",
            "Interlock_Height": "0",
            "Interlocking_Lid": "false",
            "Label_Lid": "false",
            "Label_Lid_Style": "Raised",
            "Lengthwise_Cup_Ratios": "[1, 1, 1, 1, 1]",
            "Lengthwise_Finger_Slot": "true",
            "Lid_Handle_Style": "Finger_Holes",
            "Lid_Thickness": "0.07",
            "Make_Finger_Slots": "false",
            "Make_Insert_Tray": "false",
            "Make_Room_For_Recessed_Lid_And_Stacked_Tray": "false",
            "Minimum_Storage_Slot_Separation": "0.08",
            "Number_Of_Finger_Holes": "1",
            "Rotate_Handle": "0",
            "Scale_Units": "25.4",
            "Slot_Direction": "Lengthwise",
            "Square_Cup_Size": "1",
            "Storage_Slot_Width": "0.08",
            "Storage_Wall_Width": "0.5",
            "Tray_Height": "1",
            "Tray_Length": "2",
            "Tray_Wall_Thickness": "0.07",
            "Tray_Width": "2",
            "Widthwise_Cup_Ratios": "[1, 1, 1, 1, 1]"
        },
        "big_slide_tray": {
            "Add_Corner_Posts": "false",
            "Box_Top_Height": "1",
            "Box_Top_Interlock_Height": "0.08",
            "Box_Top_Interlock_Type": "Shell",
            "Build_Mode": "Storage_Slots",
            "Corner_Post_Size": "0.2",
            "Corner_Roundness": "0.5",
            "Create_A_Box_Top": "true",
            "Create_A_Lid": "false",
            "Cups_Across_Width": "1",
            "Cups_Along_Length": "1",
            "Custom_Col_Row_Ratios": "[1, 5, 2, 2, 2, 1.5, 2, 0, 3, 0, 3, 0, 3, 0, 2, 0, 5]",
            "Custom_Division_List": "[\"-\", 0.333, 0, 0.666, \"-\", 0.666, 0.333, 1, \"|\", 0.333, 0.333, 1, \"|\", 0.666, 0, 0.666]",
            "Dimensions_Are_External": "false",
            "Divider_Wall_Height_Scale": "1",
            "Divider_Wall_Thickness": "0.08",
            "Finger_Hole_Diameter": "0.75",
            "Finger_Hole_Position": "1",
            "Finger_Hole_Style": "Round",
            "Finger_Slot_Lift": "1",
            "Finger_Slot_Position": "0.5",
            "Finger_Slot_Radius": "1",
            "Finger_Slot_Width": "0",
            "Floor_Thickness": "0.07",
            "Insert_Tray_Gap": "0.03",
            "Insert_Tray_Height": "0",
            "Interlock_Divider_Wall_Recess": "0.05",
            "Interlock_Gap": "0.008",
            "Interlock_Height": "0",
            "Interlocking_Lid": "false",
            "Label_Lid": "false",
            "Label_Lid_Style": "Raised",
            "Lengthwise_Cup_Ratios": "[1, 1, 1, 1, 1]",
            "Lengthwise_Finger_Slot": "true",
            "Lid_Handle_Style": "Finger_Holes",
            "Lid_Thickness": "0.07",
            "Make_Finger_Slots": "false",
            "Make_Insert_Tray": "false",
            "Make_Room_For_Recessed_Lid_And_Stacked_Tray": "false",
            "Minimum_Storage_Slot_Separation": "0.08",
            "Number_Of_Columns": "4",
            "Number_Of_Finger_Holes": "1",
            "Rotate_Handle": "0",
            "Scale_Units": "25.4",
            "Square_Cup_Size": "1",
            "Storage_Slot_Width": "0.08",
            "Storage_Wall_Width": "0.25",
            "Tray_Height": "1",
            "Tray_Length": "8",
            "Tray_Wall_Thickness": "0.07",
            "Tray_Width": "8",
            "Widthwise_Cup_Ratios": "[1, 1, 1, 1, 1]"
        },
        "Slide_Box_2x4": {
            "Add_Corner_Posts": "false",
            "Box_Top_Height": "1",
            "Box_Top_Interlock_Height": "0.08",
            "Box_Top_Interlock_Type": "Shell",
            "Build_Mode": "Storage_Slots",
            "Corner_Post_Size": "0.2",
            "Corner_Roundness": "0.5",
            "Create_A_Box_Top": "true",
            "Create_A_Lid": "false",
            "Cups_Across_Width": "1",
            "Cups_Along_Length": "1",
            "Custom_Col_Row_Ratios": "[1, 5, 2, 2, 2, 1.5, 2, 0, 3, 0, 3, 0, 3, 0, 2, 0, 5]",
            "Custom_Division_List": "[\"-\", 0.333, 0, 0.666, \"-\", 0.666, 0.333, 1, \"|\", 0.333, 0.333, 1, \"|\", 0.666, 0, 0.666]",
            "Dimensions_Are_External": "false",
            "Divider_Wall_Height_Scale": "1",
            "Divider_Wall_Thickness": "0.08",
            "Finger_Hole_Diameter": "0.75",
            "Finger_Hole_Position": "1",
            "Finger_Hole_Style": "Round",
            "Finger_Slot_Lift": "1",
            "Finger_Slot_Position": "0.5",
            "Finger_Slot_Radius": "1",
            "Finger_Slot_Width": "0",
            "Floor_Thickness": "0.07",
            "Insert_Tray_Gap": "0.03",
            "Insert_Tray_Height": "0",
            "Interlock_Divider_Wall_Recess": "0.05",
            "Interlock_Gap": "0.003",
            "Interlock_Height": "0",
            "Interlocking_Lid": "false",
            "Label_Lid": "false",
            "Label_Lid_Style": "Raised",
            "Lengthwise_Cup_Ratios": "[1, 1, 1, 1, 1]",
            "Lengthwise_Finger_Slot": "true",
            "Lid_Handle_Style": "Finger_Holes",
            "Lid_Thickness": "0.07",
            "Make_Finger_Slots": "false",
            "Make_Insert_Tray": "false",
            "Make_Room_For_Recessed_Lid_And_Stacked_Tray": "false",
            "Minimum_Storage_Slot_Separation": "0.04",
            "Number_Of_Columns": "2",
            "Number_Of_Finger_Holes": "1",
            "Rotate_Handle": "0",
            "Scale_Units": "25.4",
            "Square_Cup_Size": "1",
            "Storage_Slot_Width": "0.08",
            "Storage_Wall_Width": "0.2",
            "Tray_Height": "1",
            "Tray_Length": "2",
            "Tray_Wall_Thickness": "0.1",
            "Tray_Width": "4",
            "Widthwise_Cup_Ratios": "[1, 1, 1, 1, 1]",
            "With_Dividers": "true"
        },
        "Slide_Box_Bulk": {
            "Add_Corner_Posts": "false",
            "Box_Top_Height": "1",
            "Box_Top_Interlock_Height": "0.08",
            "Box_Top_Interlock_Type": "Shell",
            "Build_Mode": "Storage_Slots",
            "Corner_Post_Size": "0.2",
            "Corner_Roundness": "0.5",
            "Create_A_Box_Top": "true",
            "Create_A_Lid": "false",
            "Cups_Across_Width": "1",
            "Cups_Along_Length": "1",
            "Custom_Col_Row_Ratios": "[1, 5, 2, 2, 2, 1.5, 2, 0, 3, 0, 3, 0, 3, 0, 2, 0, 5]",
            "Custom_Division_List": "[\"-\", 0.333, 0, 0.666, \"-\", 0.666, 0.333, 1, \"|\", 0.333, 0.333, 1, \"|\", 0.666, 0, 0.666]",
            "Dimensions_Are_External": "false",
            "Divider_Wall_Height_Scale": "1",
            "Divider_Wall_Thickness": "0.08",
            "Finger_Hole_Diameter": "0.75",
            "Finger_Hole_Position": "1",
            "Finger_Hole_Style": "Round",
            "Finger_Slot_Lift": "1",
            "Finger_Slot_Position": "0.5",
            "Finger_Slot_Radius": "1",
            "Finger_Slot_Width": "0",
            "Floor_Thickness": "0.07",
            "Insert_Tray_Gap": "0.03",
            "Insert_Tray_Height": "0",
            "Interlock_Divider_Wall_Recess": "0.05",
            "Interlock_Gap": "0.008",
            "Interlock_Height": "0",
            "Interlocking_Lid": "false",
            "Label_Lid": "false",
            "Label_Lid_Style": "Raised",
            "Lengthwise_Cup_Ratios": "[1, 1, 1, 1, 1]",
            "Lengthwise_Finger_Slot": "true",
            "Lid_Handle_Style": "Finger_Holes",
            "Lid_Thickness": "0.07",
            "Make_Finger_Slots": "false",
            "Make_Insert_Tray": "false",
            "Make_Room_For_Recessed_Lid_And_Stacked_Tray": "false",
            "Minimum_Storage_Slot_Separation": "0.05",
            "Number_Of_Columns": "3",
            "Number_Of_Finger_Holes": "1",
            "Rotate_Handle": "0",
            "Scale_Units": "25.4",
            "Square_Cup_Size": "1",
            "Storage_Slot_Width": "0.5",
            "Storage_Wall_Width": "0.25",
            "Tray_Height": "1",
            "Tray_Length": "8",
            "Tray_Wall_Thickness": "0.07",
            "Tray_Width": "6",
            "Widthwise_Cup_Ratios": "[1, 1, 1, 1, 1]",
            "With_Dividers": "false"
        },
        "design default values": {
            "Add_Corner_Posts": "false",
            "Box_Top_Height": "0.75",
            "Box_Top_Interlock_Height": "0.08",
            "Box_Top_Interlock_Type": "Shell",
            "Build_Mode": "Storage_Slots",
            "Corner_Post_Size": "0.2",
            "Corner_Roundness": "0.5",
            "Create_A_Box_Top": "true",
            "Create_A_Lid": "false",
            "Cups_Across_Width": "1",
            "Cups_Along_Length": "1",
            "Custom_Col_Row_Ratios": "[1, 5, 2, 2, 2, 1.5, 2, 0, 3, 0, 3, 0, 3, 0, 2, 0, 5]",
            "Custom_Division_List": "[\"-\", 0.333, 0, 0.666, \"-\", 0.666, 0.333, 1, \"|\", 0.333, 0.333, 1, \"|\", 0.666, 0, 0.666]",
            "Detent_Factor": "0.852",
            "Detent_Orientation": "Length",
            "Detent_Radius": "1.5",
            "Dimensions_Are_External": "false",
            "Divider_Wall_Height_Scale": "1",
            "Divider_Wall_Thickness": "0.08",
            "Finger_Detents": "Two",
            "Finger_Hole_Diameter": "0.75",
            "Finger_Hole_Position": "1",
            "Finger_Hole_Style": "Round",
            "Finger_Slot_Lift": "1",
            "Finger_Slot_Position": "0.5",
            "Finger_Slot_Radius": "1",
            "Finger_Slot_Width": "0",
            "Floor_Thickness": "0.07",
            "Insert_Tray_Gap": "0.03",
            "Insert_Tray_Height": "0",
            "Interlock_Divider_Wall_Recess": "0.05",
            "Interlock_Gap": "0.003",
            "Interlock_Height": "0",
            "Interlocking_Lid": "false",
            "Label_Lid": "false",
            "Label_Lid_Style": "Raised",
            "Lengthwise_Cup_Ratios": "[1, 1, 1, 1, 1]",
            "Lengthwise_Finger_Slot": "true",
            "Lid_Handle_Style": "Finger_Holes",
            "Lid_Thickness": "0.07",
            "Make_Finger_Slots": "false",
            "Make_Insert_Tray": "false",
            "Make_Room_For_Recessed_Lid_And_Stacked_Tray": "false",
            "Minimum_Storage_Slot_Separation": "0.04",
            "Number_Of_Columns": "2",
            "Number_Of_Finger_Holes": "1",
            "Rotate_Handle": "0",
            "Scale_Units": "25.4",
            "Square_Cup_Size": "1",
            "Storage_Slot_Width": "0.08",
            "Storage_Wall_Width": "0.2",
            "Tray_Height": "1.25",
            "Tray_Length": "2",
            "Tray_Wall_Thickness": "0.1",
            "Tray_Width": "4",
            "Widthwise_Cup_Ratios": "[1, 1, 1, 1, 1]",
            "With_Dividers": "true"
        },
        "Slide_Box_4x2": {
            "Add_Corner_Posts": "false",
            "Box_Top_Height": "0.75",
            "Box_Top_Interlock_Height": "0.08",
            "Box_Top_Interlock_Type": "Shell",
            "Build_Mode": "Storage_Slots",
            "Corner_Post_Size": "0.2",
            "Corner_Roundness": "0.5",
            "Create_A_Box_Top": "true",
            "Create_A_Lid": "false",
            "Cups_Across_Width": "1",
            "Cups_Along_Length": "1",
            "Custom_Col_Row_Ratios": "[1, 5, 2, 2, 2, 1.5, 2, 0, 3, 0, 3, 0, 3, 0, 2, 0, 5]",
            "Custom_Division_List": "[\"-\", 0.333, 0, 0.666, \"-\", 0.666, 0.333, 1, \"|\", 0.333, 0.333, 1, \"|\", 0.666, 0, 0.666]",
            "Detent_Factor": "0.852",
            "Detent_Orientation": "Length",
            "Detent_Radius": "1.5",
            "Dimensions_Are_External": "false",
            "Divider_Wall_Height_Scale": "1",
            "Divider_Wall_Thickness": "0.08",
            "Finger_Detents": "Two",
            "Finger_Hole_Diameter": "0.75",
            "Finger_Hole_Position": "1",
            "Finger_Hole_Style": "Round",
            "Finger_Slot_Lift": "1",
            "Finger_Slot_Position": "0.5",
            "Finger_Slot_Radius": "1",
            "Finger_Slot_Width": "0",
            "Floor_Thickness": "0.07",
            "Insert_Tray_Gap": "0.03",
            "Insert_Tray_Height": "0",
            "Interlock_Divider_Wall_Recess": "0.05",
            "Interlock_Gap": "0.003",
            "Interlock_Height": "0",
            "Interlocking_Lid": "false",
            "Label_Lid": "false",
            "Label_Lid_Style": "Raised",
            "Lengthwise_Cup_Ratios": "[1, 1, 1, 1, 1]",
            "Lengthwise_Finger_Slot": "true",
            "Lid_Handle_Style": "Finger_Holes",
            "Lid_Thickness": "0.07",
            "Make_Finger_Slots": "false",
            "Make_Insert_Tray": "false",
            "Make_Room_For_Recessed_Lid_And_Stacked_Tray": "false",
            "Minimum_Storage_Slot_Separation": "0.04",
            "Number_Of_Columns": "2",
            "Number_Of_Finger_Holes": "1",
            "Rotate_Handle": "0",
            "Scale_Units": "25.4",
            "Square_Cup_Size": "1",
            "Storage_Slot_Width": "0.08",
            "Storage_Wall_Width": "0.2",
            "Tray_Height": "1.25",
            "Tray_Length": "2",
            "Tray_Wall_Thickness": "0.1",
            "Tray_Width": "4",
            "Widthwise_Cup_Ratios": "[1, 1, 1, 1, 1]",
            "With_Dividers": "true"
        }
    },
    "fileFormatVersion": "1"
}
